{
  "operating_systems": [
    {
      "name": "linux",
      "versions": [
        {
          "types": ["pop", "ubuntu"],
          "commands": [
            {
              "meta": {
                "command": "sudo",
                "args": ["apt-get", "update"]
              }
            },
            {
              "meta": {
                "command": "sudo",
                "args": [
                  "apt-get",
                  "upgrade",
                  "-y",
                  "--allow-downgrades",
                  "--with-new-pkgs"
                ]
              }
            },
            {
              "meta": {
                "command": "sudo",
                "args": ["apt-get", "install", "-y", "build-essential"]
              }
            },
            {
              "meta": {
                "command": "sudo",
                "args": ["apt-get", "install", "-y"],
                "apps": [
                  "apt-transport-https",
                  "ca-certificates",
                  "clamav",
                  "curl",
                  "dunst",
                  "emacs",
                  "git",
                  "gnupg",
                  "firefox",
                  "flameshot",
                  "i3",
                  "ispell",
                  "kitty",
                  "peek",
                  "git",
                  "gimp",
                  "kdenlive",
                  "krita",
                  "libffi-dev",
                  "libnotify-bin",
                  "libssl-dev",
                  "libx11-dev",
                  "libx11-xcb-dev",
                  "libxcursor-dev",
                  "libxss-dev",
                  "lsb-release",
                  "magnus",
                  "neovim",
                  "nmap",
                  "obs-studio",
                  "openssh-client",
                  "pkg-config",
                  "python3",
                  "python3-pip",
                  "pulseaudio",
                  "rofi",
                  "rsync",
                  "shellcheck",
                  "systemtap-sdt-dev",
                  "tmux",
                  "vlc",
                  "weechat",
                  "wget",
                  "youtube-dl",
                  "xsel",
                  "zsh"
                ]
              }
            }
          ]
        },
        {
          "types": ["arch", "endeavouros"],
          "commands": [
            {
              "meta": {
                "command": "sudo",
                "args": ["pacman", "-S"],
                "apps": [
                  "clamav",
                  "flameshot",
                  "gimp",
                  "gnupg",
                  "git",
                  "i3",
                  "ispell",
                  "krita",
                  "kdenlive",
                  "kitty",
                  "magnus",
                  "neovim",
                  "nmap",
                  "obs",
                  "peek",
                  "shellcheck",
                  "tmux",
                  "vlc",
                  "weechat",
                  "xcolor",
                  "zsh"
                ]
              }
            }
          ]
        },
        {
          "types": ["shared"],
          "commands": [
            {
              "meta": {
                "command": "cargo",
                "args": ["install"],
                "apps": [
                  "bacon",
                  "bat",
                  "bob-nvim",
                  "cargo-asm",
                  "cargo-expand",
                  "cargo-watch",
                  "coreutils",
                  "deno",
                  "dtool",
                  "dust",
                  "exa",
                  "gitui",
                  "irust",
                  "pastel",
                  "rg",
                  "rls",
                  "rust-lldb",
                  "rtx",
                  "rustc",
                  "rust-gdb",
                  "rust-gdbgui",
                  "sccache",
                  "simple-http-server",
                  "speedtest-rs",
                  "starship",
                  "stylua",
                  "t-rec",
                  "watchexec",
                  "xcolor",
                  "zellij"
                ]
              }
            }
          ]
        }
      ]
    }
  ]
}
